pyYify/__init__.py
pyYify/yify.py
pyYify-1.9.1.dist-info/DESCRIPTION.rst
pyYify-1.9.1.dist-info/METADATA
pyYify-1.9.1.dist-info/RECORD
pyYify-1.9.1.dist-info/WHEEL
pyYify-1.9.1.dist-info/metadata.json
pyYify-1.9.1.dist-info/top_level.txt
