Metadata-Version: 2.0
Name: pyYify
Version: 1.9.1
Summary: This Module is used to get the Top seeded torrents at any given time and get the entire movie details and ratings . Its also useful to search for any movie using different parameters and obtain their magnet link or torrent file of any prefered quality.
Home-page: https://github.com/nateshmbhat/Yify-Python
Author: Natesh M Bhat
Author-email: nateshmbhatofficial@gmail.com
License: MIT
Keywords: yify,torrent-python,movie-torrent,torrent,pyyify,Yify,yify torrent,yify download,download yify,yifyer,yifypy,torrent download,movie torrent,movie downloader,movie finder
Platform: UNKNOWN
Classifier: Programming Language :: Python :: 3.2
Classifier: Programming Language :: Python :: 3.3
Classifier: Programming Language :: Python :: 3.4
Requires-Dist: bs4
Requires-Dist: requests
Requires-Dist: urllib
Requires-Dist: urllib3
